dataclasses_ujson/__init__.py
dataclasses_ujson/dataclasses_ujson.py
dataclasses_ujson-0.0.14.dist-info/LICENSE.txt
dataclasses_ujson-0.0.14.dist-info/METADATA
dataclasses_ujson-0.0.14.dist-info/WHEEL
dataclasses_ujson-0.0.14.dist-info/top_level.txt
dataclasses_ujson-0.0.14.dist-info/RECORD
