Metadata-Version: 2.1
Name: dataclasses-ujson
Version: 0.0.14
Summary: fast converter your json to dataclass
Home-page: https://github.com/kislenko-artem/dataclasses-ujson
Author: Kislenko Artem 
Author-email: artem@webart-tech.ru
License: Apache
Platform: UNKNOWN
Requires-Python: >=3.7
Requires-Dist: ujson (>=1.35)
Provides-Extra: dev
Requires-Dist: pytest ; extra == 'dev'
